[
    {
        "id": "coingecko_price",
        "name": "CoinGecko Price",
        "description": "Get real-time cryptocurrency prices, market data, and coin information",
        "category": "Finance",
        "provider": "CoinGecko",
        "authType": "none",
        "baseUrl": "https://api.coingecko.com/api/v3",
        "cors": true,
        "endpoints": [
            {
                "name": "getPrice",
                "method": "GET",
                "path": "/simple/price",
                "params": [
                    {
                        "name": "ids",
                        "type": "string",
                        "required": true,
                        "desc": "Coin IDs (bitcoin,ethereum)"
                    },
                    {
                        "name": "vs_currencies",
                        "type": "string",
                        "required": true,
                        "desc": "Target currencies (usd,eur)"
                    }
                ]
            },
            {
                "name": "getCoinList",
                "method": "GET",
                "path": "/coins/list",
                "params": []
            },
            {
                "name": "getTrending",
                "method": "GET",
                "path": "/search/trending",
                "params": []
            }
        ]
    },
    {
        "id": "exchangerate",
        "name": "Exchange Rate",
        "description": "Free currency exchange rates and conversion",
        "category": "Finance",
        "provider": "ExchangeRate-API",
        "authType": "none",
        "baseUrl": "https://open.er-api.com/v6",
        "cors": true,
        "endpoints": [
            {
                "name": "getLatest",
                "method": "GET",
                "path": "/latest/{base}",
                "params": [
                    {
                        "name": "base",
                        "type": "string",
                        "required": true,
                        "desc": "Base currency code (USD)"
                    }
                ]
            }
        ]
    },
    {
        "id": "alpha_vantage",
        "name": "Alpha Vantage",
        "description": "Realtime and historical stock market data, forex, crypto",
        "category": "Finance",
        "provider": "Alpha Vantage",
        "authType": "apiKey",
        "baseUrl": "https://www.alphavantage.co",
        "cors": true,
        "endpoints": [
            {
                "name": "stockQuote",
                "method": "GET",
                "path": "/query",
                "params": [
                    {
                        "name": "function",
                        "type": "string",
                        "required": true,
                        "desc": "GLOBAL_QUOTE"
                    },
                    {
                        "name": "symbol",
                        "type": "string",
                        "required": true,
                        "desc": "Stock symbol (AAPL)"
                    },
                    {
                        "name": "apikey",
                        "type": "string",
                        "required": true,
                        "desc": "API key"
                    }
                ]
            }
        ]
    },
    {
        "id": "finnhub",
        "name": "Finnhub",
        "description": "Real-time stock data, company profiles, and financial news",
        "category": "Finance",
        "provider": "Finnhub",
        "authType": "apiKey",
        "baseUrl": "https://finnhub.io/api/v1",
        "cors": true,
        "endpoints": [
            {
                "name": "quote",
                "method": "GET",
                "path": "/quote",
                "params": [
                    {
                        "name": "symbol",
                        "type": "string",
                        "required": true,
                        "desc": "Stock symbol"
                    },
                    {
                        "name": "token",
                        "type": "string",
                        "required": true,
                        "desc": "API token"
                    }
                ]
            },
            {
                "name": "companyProfile",
                "method": "GET",
                "path": "/stock/profile2",
                "params": [
                    {
                        "name": "symbol",
                        "type": "string",
                        "required": true,
                        "desc": "Stock symbol"
                    },
                    {
                        "name": "token",
                        "type": "string",
                        "required": true,
                        "desc": "API token"
                    }
                ]
            }
        ]
    },
    {
        "id": "marketaux",
        "name": "MarketAux News",
        "description": "Live stock market news with sentiment analysis",
        "category": "Finance",
        "provider": "MarketAux",
        "authType": "apiKey",
        "baseUrl": "https://api.marketaux.com/v1",
        "cors": true,
        "endpoints": [
            {
                "name": "getNews",
                "method": "GET",
                "path": "/news/all",
                "params": [
                    {
                        "name": "api_token",
                        "type": "string",
                        "required": true,
                        "desc": "API token"
                    },
                    {
                        "name": "symbols",
                        "type": "string",
                        "required": false,
                        "desc": "Stock symbols"
                    }
                ]
            }
        ]
    },
    {
        "id": "econdb",
        "name": "EconDB",
        "description": "Global macroeconomic data — GDP, inflation, unemployment",
        "category": "Finance",
        "provider": "EconDB",
        "authType": "none",
        "baseUrl": "https://www.econdb.com/api",
        "cors": true,
        "endpoints": [
            {
                "name": "getSeries",
                "method": "GET",
                "path": "/series/",
                "params": [
                    {
                        "name": "ticker",
                        "type": "string",
                        "required": true,
                        "desc": "Data series ticker"
                    }
                ]
            }
        ]
    },
    {
        "id": "gnews",
        "name": "GNews",
        "description": "Search for news articles from thousands of sources worldwide",
        "category": "Market Research",
        "provider": "GNews",
        "authType": "apiKey",
        "baseUrl": "https://gnews.io/api/v4",
        "cors": true,
        "endpoints": [
            {
                "name": "search",
                "method": "GET",
                "path": "/search",
                "params": [
                    {
                        "name": "q",
                        "type": "string",
                        "required": true,
                        "desc": "Search query"
                    },
                    {
                        "name": "token",
                        "type": "string",
                        "required": true,
                        "desc": "API token"
                    },
                    {
                        "name": "lang",
                        "type": "string",
                        "required": false,
                        "desc": "Language (en)"
                    }
                ]
            },
            {
                "name": "topHeadlines",
                "method": "GET",
                "path": "/top-headlines",
                "params": [
                    {
                        "name": "token",
                        "type": "string",
                        "required": true,
                        "desc": "API key"
                    },
                    {
                        "name": "category",
                        "type": "string",
                        "required": false,
                        "desc": "business,technology,etc"
                    }
                ]
            }
        ]
    },
    {
        "id": "currents",
        "name": "Currents API",
        "description": "Latest news from blogs, forums, and news sources",
        "category": "Market Research",
        "provider": "Currents",
        "authType": "apiKey",
        "baseUrl": "https://api.currentsapi.services/v1",
        "cors": true,
        "endpoints": [
            {
                "name": "search",
                "method": "GET",
                "path": "/search",
                "params": [
                    {
                        "name": "apiKey",
                        "type": "string",
                        "required": true,
                        "desc": "API key"
                    },
                    {
                        "name": "keywords",
                        "type": "string",
                        "required": false,
                        "desc": "Keywords"
                    }
                ]
            },
            {
                "name": "latest",
                "method": "GET",
                "path": "/latest-news",
                "params": [
                    {
                        "name": "apiKey",
                        "type": "string",
                        "required": true,
                        "desc": "API key"
                    }
                ]
            }
        ]
    },
    {
        "id": "hackernews",
        "name": "Hacker News",
        "description": "Tech news, stories, and discussions from Y Combinator",
        "category": "Market Research",
        "provider": "HackerNews",
        "authType": "none",
        "baseUrl": "https://hacker-news.firebaseio.com/v0",
        "cors": true,
        "endpoints": [
            {
                "name": "topStories",
                "method": "GET",
                "path": "/topstories.json",
                "params": []
            },
            {
                "name": "getItem",
                "method": "GET",
                "path": "/item/{id}.json",
                "params": [
                    {
                        "name": "id",
                        "type": "number",
                        "required": true,
                        "desc": "Item ID"
                    }
                ]
            }
        ]
    },
    {
        "id": "producthunt",
        "name": "Product Hunt",
        "description": "Discover new tech products, startups, and tools",
        "category": "Market Research",
        "provider": "ProductHunt",
        "authType": "apiKey",
        "baseUrl": "https://api.producthunt.com/v2/api/graphql",
        "cors": false,
        "endpoints": [
            {
                "name": "getPosts",
                "method": "POST",
                "path": "",
                "params": [
                    {
                        "name": "query",
                        "type": "string",
                        "required": true,
                        "desc": "GraphQL query"
                    }
                ]
            }
        ]
    },
    {
        "id": "reddit_search",
        "name": "Reddit Search",
        "description": "Search Reddit posts, comments, and subreddits for market intelligence",
        "category": "Market Research",
        "provider": "Reddit",
        "authType": "none",
        "baseUrl": "https://www.reddit.com",
        "cors": true,
        "endpoints": [
            {
                "name": "search",
                "method": "GET",
                "path": "/search.json",
                "params": [
                    {
                        "name": "q",
                        "type": "string",
                        "required": true,
                        "desc": "Search query"
                    },
                    {
                        "name": "sort",
                        "type": "string",
                        "required": false,
                        "desc": "relevance,hot,new,top"
                    }
                ]
            },
            {
                "name": "subreddit",
                "method": "GET",
                "path": "/r/{subreddit}/top.json",
                "params": [
                    {
                        "name": "subreddit",
                        "type": "string",
                        "required": true,
                        "desc": "Subreddit name"
                    },
                    {
                        "name": "t",
                        "type": "string",
                        "required": false,
                        "desc": "Time: day,week,month,year"
                    }
                ]
            }
        ]
    },
    {
        "id": "hunter_email",
        "name": "Hunter.io",
        "description": "Find and verify professional email addresses for outreach",
        "category": "Market Research",
        "provider": "Hunter",
        "authType": "apiKey",
        "baseUrl": "https://api.hunter.io/v2",
        "cors": true,
        "endpoints": [
            {
                "name": "domainSearch",
                "method": "GET",
                "path": "/domain-search",
                "params": [
                    {
                        "name": "domain",
                        "type": "string",
                        "required": true,
                        "desc": "Company domain"
                    },
                    {
                        "name": "api_key",
                        "type": "string",
                        "required": true,
                        "desc": "API key"
                    }
                ]
            },
            {
                "name": "emailVerify",
                "method": "GET",
                "path": "/email-verifier",
                "params": [
                    {
                        "name": "email",
                        "type": "string",
                        "required": true,
                        "desc": "Email to verify"
                    },
                    {
                        "name": "api_key",
                        "type": "string",
                        "required": true,
                        "desc": "API key"
                    }
                ]
            }
        ]
    },
    {
        "id": "clearbit_logo",
        "name": "Clearbit Logo",
        "description": "Get company logos by domain name",
        "category": "Market Research",
        "provider": "Clearbit",
        "authType": "none",
        "baseUrl": "https://logo.clearbit.com",
        "cors": true,
        "endpoints": [
            {
                "name": "getLogo",
                "method": "GET",
                "path": "/{domain}",
                "params": [
                    {
                        "name": "domain",
                        "type": "string",
                        "required": true,
                        "desc": "Company domain (stripe.com)"
                    }
                ]
            }
        ]
    },
    {
        "id": "github_api",
        "name": "GitHub",
        "description": "Access repos, issues, PRs, users, and organizations on GitHub",
        "category": "Development",
        "provider": "GitHub",
        "authType": "optional",
        "baseUrl": "https://api.github.com",
        "cors": true,
        "endpoints": [
            {
                "name": "searchRepos",
                "method": "GET",
                "path": "/search/repositories",
                "params": [
                    {
                        "name": "q",
                        "type": "string",
                        "required": true,
                        "desc": "Search query"
                    },
                    {
                        "name": "sort",
                        "type": "string",
                        "required": false,
                        "desc": "stars,forks,updated"
                    }
                ]
            },
            {
                "name": "getRepo",
                "method": "GET",
                "path": "/repos/{owner}/{repo}",
                "params": [
                    {
                        "name": "owner",
                        "type": "string",
                        "required": true,
                        "desc": "Owner"
                    },
                    {
                        "name": "repo",
                        "type": "string",
                        "required": true,
                        "desc": "Repo name"
                    }
                ]
            },
            {
                "name": "listIssues",
                "method": "GET",
                "path": "/repos/{owner}/{repo}/issues",
                "params": [
                    {
                        "name": "owner",
                        "type": "string",
                        "required": true,
                        "desc": "Owner"
                    },
                    {
                        "name": "repo",
                        "type": "string",
                        "required": true,
                        "desc": "Repo name"
                    }
                ]
            }
        ]
    },
    {
        "id": "uptimerobot",
        "name": "UptimeRobot",
        "description": "Website uptime monitoring and alerting",
        "category": "Development",
        "provider": "UptimeRobot",
        "authType": "apiKey",
        "baseUrl": "https://api.uptimerobot.com/v2",
        "cors": false,
        "endpoints": [
            {
                "name": "getMonitors",
                "method": "POST",
                "path": "/getMonitors",
                "params": [
                    {
                        "name": "api_key",
                        "type": "string",
                        "required": true,
                        "desc": "API key"
                    }
                ]
            }
        ]
    },
    {
        "id": "jsonplaceholder",
        "name": "JSONPlaceholder",
        "description": "Fake REST API for testing and prototyping",
        "category": "Development",
        "provider": "Typicode",
        "authType": "none",
        "baseUrl": "https://jsonplaceholder.typicode.com",
        "cors": true,
        "endpoints": [
            {
                "name": "getPosts",
                "method": "GET",
                "path": "/posts",
                "params": []
            },
            {
                "name": "getUsers",
                "method": "GET",
                "path": "/users",
                "params": []
            }
        ]
    },
    {
        "id": "httpbin",
        "name": "HTTPBin",
        "description": "HTTP request and response service for testing",
        "category": "Development",
        "provider": "HTTPBin",
        "authType": "none",
        "baseUrl": "https://httpbin.org",
        "cors": true,
        "endpoints": [
            {
                "name": "get",
                "method": "GET",
                "path": "/get",
                "params": []
            },
            {
                "name": "post",
                "method": "POST",
                "path": "/post",
                "params": []
            },
            {
                "name": "ip",
                "method": "GET",
                "path": "/ip",
                "params": []
            }
        ]
    },
    {
        "id": "spacex",
        "name": "SpaceX Data",
        "description": "SpaceX launches, rockets, capsules, and history",
        "category": "Development",
        "provider": "SpaceX",
        "authType": "none",
        "baseUrl": "https://api.spacexdata.com/v4",
        "cors": true,
        "endpoints": [
            {
                "name": "launches",
                "method": "GET",
                "path": "/launches",
                "params": []
            },
            {
                "name": "latestLaunch",
                "method": "GET",
                "path": "/launches/latest",
                "params": []
            }
        ]
    },
    {
        "id": "openweathermap",
        "name": "OpenWeatherMap",
        "description": "Current weather, forecasts, and historical weather data",
        "category": "Data & Analytics",
        "provider": "OpenWeather",
        "authType": "apiKey",
        "baseUrl": "https://api.openweathermap.org/data/2.5",
        "cors": true,
        "endpoints": [
            {
                "name": "current",
                "method": "GET",
                "path": "/weather",
                "params": [
                    {
                        "name": "q",
                        "type": "string",
                        "required": true,
                        "desc": "City name"
                    },
                    {
                        "name": "appid",
                        "type": "string",
                        "required": true,
                        "desc": "API key"
                    },
                    {
                        "name": "units",
                        "type": "string",
                        "required": false,
                        "desc": "metric,imperial"
                    }
                ]
            },
            {
                "name": "forecast",
                "method": "GET",
                "path": "/forecast",
                "params": [
                    {
                        "name": "q",
                        "type": "string",
                        "required": true,
                        "desc": "City name"
                    },
                    {
                        "name": "appid",
                        "type": "string",
                        "required": true,
                        "desc": "API key"
                    }
                ]
            }
        ]
    },
    {
        "id": "ip_geolocation",
        "name": "IP Geolocation",
        "description": "Get geographic location from IP address",
        "category": "Data & Analytics",
        "provider": "ipapi",
        "authType": "none",
        "baseUrl": "https://ipapi.co",
        "cors": true,
        "endpoints": [
            {
                "name": "lookup",
                "method": "GET",
                "path": "/{ip}/json",
                "params": [
                    {
                        "name": "ip",
                        "type": "string",
                        "required": true,
                        "desc": "IP address"
                    }
                ]
            },
            {
                "name": "myIp",
                "method": "GET",
                "path": "/json",
                "params": []
            }
        ]
    },
    {
        "id": "rest_countries",
        "name": "REST Countries",
        "description": "Country data — population, languages, currencies, flags",
        "category": "Data & Analytics",
        "provider": "RestCountries",
        "authType": "none",
        "baseUrl": "https://restcountries.com/v3.1",
        "cors": true,
        "endpoints": [
            {
                "name": "all",
                "method": "GET",
                "path": "/all",
                "params": []
            },
            {
                "name": "byName",
                "method": "GET",
                "path": "/name/{name}",
                "params": [
                    {
                        "name": "name",
                        "type": "string",
                        "required": true,
                        "desc": "Country name"
                    }
                ]
            }
        ]
    },
    {
        "id": "calendarific",
        "name": "Calendarific",
        "description": "Public holidays and observances for 200+ countries",
        "category": "Data & Analytics",
        "provider": "Calendarific",
        "authType": "apiKey",
        "baseUrl": "https://calendarific.com/api/v2",
        "cors": true,
        "endpoints": [
            {
                "name": "holidays",
                "method": "GET",
                "path": "/holidays",
                "params": [
                    {
                        "name": "api_key",
                        "type": "string",
                        "required": true,
                        "desc": "API key"
                    },
                    {
                        "name": "country",
                        "type": "string",
                        "required": true,
                        "desc": "Country code (US)"
                    },
                    {
                        "name": "year",
                        "type": "number",
                        "required": true,
                        "desc": "Year"
                    }
                ]
            }
        ]
    },
    {
        "id": "countapi",
        "name": "CountAPI",
        "description": "Simple counting and statistics API for tracking hits/events",
        "category": "Data & Analytics",
        "provider": "CountAPI",
        "authType": "none",
        "baseUrl": "https://api.countapi.xyz",
        "cors": true,
        "endpoints": [
            {
                "name": "hit",
                "method": "GET",
                "path": "/hit/{namespace}/{key}",
                "params": [
                    {
                        "name": "namespace",
                        "type": "string",
                        "required": true,
                        "desc": "Namespace"
                    },
                    {
                        "name": "key",
                        "type": "string",
                        "required": true,
                        "desc": "Key"
                    }
                ]
            },
            {
                "name": "get",
                "method": "GET",
                "path": "/get/{namespace}/{key}",
                "params": [
                    {
                        "name": "namespace",
                        "type": "string",
                        "required": true,
                        "desc": "Namespace"
                    },
                    {
                        "name": "key",
                        "type": "string",
                        "required": true,
                        "desc": "Key"
                    }
                ]
            }
        ]
    },
    {
        "id": "unsplash",
        "name": "Unsplash",
        "description": "High-quality free stock photos for content and marketing",
        "category": "Content",
        "provider": "Unsplash",
        "authType": "apiKey",
        "baseUrl": "https://api.unsplash.com",
        "cors": true,
        "endpoints": [
            {
                "name": "searchPhotos",
                "method": "GET",
                "path": "/search/photos",
                "params": [
                    {
                        "name": "query",
                        "type": "string",
                        "required": true,
                        "desc": "Search term"
                    },
                    {
                        "name": "client_id",
                        "type": "string",
                        "required": true,
                        "desc": "API key"
                    }
                ]
            },
            {
                "name": "randomPhoto",
                "method": "GET",
                "path": "/photos/random",
                "params": [
                    {
                        "name": "client_id",
                        "type": "string",
                        "required": true,
                        "desc": "API key"
                    }
                ]
            }
        ]
    },
    {
        "id": "pexels",
        "name": "Pexels",
        "description": "Free stock photos and videos for commercial use",
        "category": "Content",
        "provider": "Pexels",
        "authType": "apiKey",
        "baseUrl": "https://api.pexels.com/v1",
        "cors": true,
        "endpoints": [
            {
                "name": "searchPhotos",
                "method": "GET",
                "path": "/search",
                "params": [
                    {
                        "name": "query",
                        "type": "string",
                        "required": true,
                        "desc": "Search term"
                    }
                ]
            },
            {
                "name": "curated",
                "method": "GET",
                "path": "/curated",
                "params": []
            }
        ]
    },
    {
        "id": "deepl_translate",
        "name": "DeepL Translator",
        "description": "High-quality AI-powered language translation",
        "category": "Content",
        "provider": "DeepL",
        "authType": "apiKey",
        "baseUrl": "https://api-free.deepl.com/v2",
        "cors": false,
        "endpoints": [
            {
                "name": "translate",
                "method": "POST",
                "path": "/translate",
                "params": [
                    {
                        "name": "text",
                        "type": "string",
                        "required": true,
                        "desc": "Text to translate"
                    },
                    {
                        "name": "target_lang",
                        "type": "string",
                        "required": true,
                        "desc": "Target language (EN,DE,FR)"
                    }
                ]
            }
        ]
    },
    {
        "id": "quotable",
        "name": "Quotable",
        "description": "Random inspirational quotes for content creation",
        "category": "Content",
        "provider": "Quotable",
        "authType": "none",
        "baseUrl": "https://api.quotable.io",
        "cors": true,
        "endpoints": [
            {
                "name": "random",
                "method": "GET",
                "path": "/random",
                "params": []
            },
            {
                "name": "search",
                "method": "GET",
                "path": "/search/quotes",
                "params": [
                    {
                        "name": "query",
                        "type": "string",
                        "required": true,
                        "desc": "Search term"
                    }
                ]
            }
        ]
    },
    {
        "id": "randomuser",
        "name": "Random User Generator",
        "description": "Generate fake user profiles for testing and prototyping",
        "category": "Productivity",
        "provider": "RandomUser",
        "authType": "none",
        "baseUrl": "https://randomuser.me",
        "cors": true,
        "endpoints": [
            {
                "name": "generate",
                "method": "GET",
                "path": "/api",
                "params": [
                    {
                        "name": "results",
                        "type": "number",
                        "required": false,
                        "desc": "Number of users"
                    },
                    {
                        "name": "nat",
                        "type": "string",
                        "required": false,
                        "desc": "Nationality (us,gb)"
                    }
                ]
            }
        ]
    },
    {
        "id": "genderize",
        "name": "Genderize",
        "description": "Predict gender based on first name — useful for personalization",
        "category": "Productivity",
        "provider": "Genderize",
        "authType": "none",
        "baseUrl": "https://api.genderize.io",
        "cors": true,
        "endpoints": [
            {
                "name": "predict",
                "method": "GET",
                "path": "/",
                "params": [
                    {
                        "name": "name",
                        "type": "string",
                        "required": true,
                        "desc": "First name"
                    }
                ]
            }
        ]
    },
    {
        "id": "agify",
        "name": "Agify",
        "description": "Predict age based on first name — demographic insights",
        "category": "Productivity",
        "provider": "Agify",
        "authType": "none",
        "baseUrl": "https://api.agify.io",
        "cors": true,
        "endpoints": [
            {
                "name": "predict",
                "method": "GET",
                "path": "/",
                "params": [
                    {
                        "name": "name",
                        "type": "string",
                        "required": true,
                        "desc": "First name"
                    }
                ]
            }
        ]
    },
    {
        "id": "nationalize",
        "name": "Nationalize",
        "description": "Predict nationality from name — useful for localization",
        "category": "Productivity",
        "provider": "Nationalize",
        "authType": "none",
        "baseUrl": "https://api.nationalize.io",
        "cors": true,
        "endpoints": [
            {
                "name": "predict",
                "method": "GET",
                "path": "/",
                "params": [
                    {
                        "name": "name",
                        "type": "string",
                        "required": true,
                        "desc": "First name"
                    }
                ]
            }
        ]
    },
    {
        "id": "ipify",
        "name": "ipify",
        "description": "Get the caller's public IP address",
        "category": "Productivity",
        "provider": "ipify",
        "authType": "none",
        "baseUrl": "https://api.ipify.org",
        "cors": true,
        "endpoints": [
            {
                "name": "getIp",
                "method": "GET",
                "path": "/",
                "params": [
                    {
                        "name": "format",
                        "type": "string",
                        "required": false,
                        "desc": "json"
                    }
                ]
            }
        ]
    },
    {
        "id": "advice_slip",
        "name": "Advice Slip",
        "description": "Random advice for daily tips or motivational content",
        "category": "Productivity",
        "provider": "AdviceSlip",
        "authType": "none",
        "baseUrl": "https://api.adviceslip.com",
        "cors": true,
        "endpoints": [
            {
                "name": "random",
                "method": "GET",
                "path": "/advice",
                "params": []
            },
            {
                "name": "search",
                "method": "GET",
                "path": "/advice/search/{query}",
                "params": [
                    {
                        "name": "query",
                        "type": "string",
                        "required": true,
                        "desc": "Search term"
                    }
                ]
            }
        ]
    },
    {
        "id": "useless_facts",
        "name": "Useless Facts",
        "description": "Random fun facts for engagement content",
        "category": "Content",
        "provider": "UselessFacts",
        "authType": "none",
        "baseUrl": "https://uselessfacts.jsph.pl/api/v2",
        "cors": true,
        "endpoints": [
            {
                "name": "random",
                "method": "GET",
                "path": "/facts/random",
                "params": []
            },
            {
                "name": "today",
                "method": "GET",
                "path": "/facts/today",
                "params": []
            }
        ]
    },
    {
        "id": "domainsdb",
        "name": "DomainsDB",
        "description": "Search registered domain names for competitor research",
        "category": "Market Research",
        "provider": "DomainsDB",
        "authType": "none",
        "baseUrl": "https://api.domainsdb.info/v1",
        "cors": true,
        "endpoints": [
            {
                "name": "search",
                "method": "GET",
                "path": "/domains/search",
                "params": [
                    {
                        "name": "domain",
                        "type": "string",
                        "required": true,
                        "desc": "Domain pattern"
                    },
                    {
                        "name": "zone",
                        "type": "string",
                        "required": false,
                        "desc": "TLD zone (com,org)"
                    }
                ]
            }
        ]
    },
    {
        "id": "tomba_email",
        "name": "Tomba Email Finder",
        "description": "Find professional email addresses for B2B sales outreach",
        "category": "Communication",
        "provider": "Tomba",
        "authType": "apiKey",
        "baseUrl": "https://api.tomba.io/v1",
        "cors": true,
        "endpoints": [
            {
                "name": "domainSearch",
                "method": "GET",
                "path": "/domain-search",
                "params": [
                    {
                        "name": "domain",
                        "type": "string",
                        "required": true,
                        "desc": "Company domain"
                    }
                ]
            },
            {
                "name": "emailFinder",
                "method": "GET",
                "path": "/email-finder",
                "params": [
                    {
                        "name": "domain",
                        "type": "string",
                        "required": true,
                        "desc": "Company domain"
                    },
                    {
                        "name": "first_name",
                        "type": "string",
                        "required": true,
                        "desc": "First name"
                    },
                    {
                        "name": "last_name",
                        "type": "string",
                        "required": true,
                        "desc": "Last name"
                    }
                ]
            }
        ]
    },
    {
        "id": "discord_webhook",
        "name": "Discord Webhook",
        "description": "Send messages and notifications to Discord channels",
        "category": "Communication",
        "provider": "Discord",
        "authType": "webhook",
        "baseUrl": "https://discord.com/api/webhooks",
        "cors": false,
        "endpoints": [
            {
                "name": "sendMessage",
                "method": "POST",
                "path": "/{webhook_id}/{webhook_token}",
                "params": [
                    {
                        "name": "content",
                        "type": "string",
                        "required": true,
                        "desc": "Message content"
                    }
                ]
            }
        ]
    },
    {
        "id": "slack_webhook",
        "name": "Slack Webhook",
        "description": "Send messages and alerts to Slack channels",
        "category": "Communication",
        "provider": "Slack",
        "authType": "webhook",
        "baseUrl": "https://hooks.slack.com",
        "cors": false,
        "endpoints": [
            {
                "name": "sendMessage",
                "method": "POST",
                "path": "/services/{webhook_path}",
                "params": [
                    {
                        "name": "text",
                        "type": "string",
                        "required": true,
                        "desc": "Message text"
                    }
                ]
            }
        ]
    },
    {
        "id": "sendgrid",
        "name": "SendGrid Email",
        "description": "Send transactional and marketing emails at scale",
        "category": "Communication",
        "provider": "SendGrid",
        "authType": "apiKey",
        "baseUrl": "https://api.sendgrid.com/v3",
        "cors": false,
        "endpoints": [
            {
                "name": "sendEmail",
                "method": "POST",
                "path": "/mail/send",
                "params": [
                    {
                        "name": "personalizations",
                        "type": "array",
                        "required": true,
                        "desc": "Recipients array"
                    },
                    {
                        "name": "from",
                        "type": "object",
                        "required": true,
                        "desc": "Sender"
                    },
                    {
                        "name": "content",
                        "type": "array",
                        "required": true,
                        "desc": "Email content"
                    }
                ]
            }
        ]
    },
    {
        "id": "mailchimp",
        "name": "Mailchimp",
        "description": "Email marketing campaigns and audience management",
        "category": "Communication",
        "provider": "Mailchimp",
        "authType": "apiKey",
        "baseUrl": "https://us1.api.mailchimp.com/3.0",
        "cors": false,
        "endpoints": [
            {
                "name": "getLists",
                "method": "GET",
                "path": "/lists",
                "params": []
            },
            {
                "name": "addMember",
                "method": "POST",
                "path": "/lists/{list_id}/members",
                "params": [
                    {
                        "name": "email_address",
                        "type": "string",
                        "required": true,
                        "desc": "Email"
                    },
                    {
                        "name": "status",
                        "type": "string",
                        "required": true,
                        "desc": "subscribed,pending"
                    }
                ]
            }
        ]
    },
    {
        "id": "notion_api",
        "name": "Notion",
        "description": "Create and manage Notion pages, databases, and blocks",
        "category": "Productivity",
        "provider": "Notion",
        "authType": "apiKey",
        "baseUrl": "https://api.notion.com/v1",
        "cors": false,
        "endpoints": [
            {
                "name": "searchPages",
                "method": "POST",
                "path": "/search",
                "params": [
                    {
                        "name": "query",
                        "type": "string",
                        "required": false,
                        "desc": "Search term"
                    }
                ]
            },
            {
                "name": "createPage",
                "method": "POST",
                "path": "/pages",
                "params": [
                    {
                        "name": "parent",
                        "type": "object",
                        "required": true,
                        "desc": "Parent database/page"
                    },
                    {
                        "name": "properties",
                        "type": "object",
                        "required": true,
                        "desc": "Page properties"
                    }
                ]
            }
        ]
    },
    {
        "id": "trello_api",
        "name": "Trello",
        "description": "Manage boards, lists, and cards for project management",
        "category": "Productivity",
        "provider": "Trello",
        "authType": "apiKey",
        "baseUrl": "https://api.trello.com/1",
        "cors": true,
        "endpoints": [
            {
                "name": "getBoards",
                "method": "GET",
                "path": "/members/me/boards",
                "params": [
                    {
                        "name": "key",
                        "type": "string",
                        "required": true,
                        "desc": "API key"
                    },
                    {
                        "name": "token",
                        "type": "string",
                        "required": true,
                        "desc": "Token"
                    }
                ]
            },
            {
                "name": "createCard",
                "method": "POST",
                "path": "/cards",
                "params": [
                    {
                        "name": "name",
                        "type": "string",
                        "required": true,
                        "desc": "Card name"
                    },
                    {
                        "name": "idList",
                        "type": "string",
                        "required": true,
                        "desc": "List ID"
                    }
                ]
            }
        ]
    },
    {
        "id": "openstreetmap",
        "name": "OpenStreetMap Nominatim",
        "description": "Geocoding and reverse geocoding — address to coordinates",
        "category": "Location",
        "provider": "OpenStreetMap",
        "authType": "none",
        "baseUrl": "https://nominatim.openstreetmap.org",
        "cors": true,
        "endpoints": [
            {
                "name": "search",
                "method": "GET",
                "path": "/search",
                "params": [
                    {
                        "name": "q",
                        "type": "string",
                        "required": true,
                        "desc": "Address or place"
                    },
                    {
                        "name": "format",
                        "type": "string",
                        "required": true,
                        "desc": "json"
                    }
                ]
            },
            {
                "name": "reverse",
                "method": "GET",
                "path": "/reverse",
                "params": [
                    {
                        "name": "lat",
                        "type": "number",
                        "required": true,
                        "desc": "Latitude"
                    },
                    {
                        "name": "lon",
                        "type": "number",
                        "required": true,
                        "desc": "Longitude"
                    },
                    {
                        "name": "format",
                        "type": "string",
                        "required": true,
                        "desc": "json"
                    }
                ]
            }
        ]
    },
    {
        "id": "spaceflight_news",
        "name": "Spaceflight News",
        "description": "Latest spaceflight and aerospace industry news",
        "category": "Content",
        "provider": "SNAPI",
        "authType": "none",
        "baseUrl": "https://api.spaceflightnewsapi.net/v4",
        "cors": true,
        "endpoints": [
            {
                "name": "articles",
                "method": "GET",
                "path": "/articles",
                "params": [
                    {
                        "name": "limit",
                        "type": "number",
                        "required": false,
                        "desc": "Number of articles"
                    }
                ]
            },
            {
                "name": "search",
                "method": "GET",
                "path": "/articles",
                "params": [
                    {
                        "name": "search",
                        "type": "string",
                        "required": true,
                        "desc": "Search term"
                    }
                ]
            }
        ]
    },
    {
        "id": "fed_treasury",
        "name": "US Treasury Data",
        "description": "Federal fiscal data — debt, spending, revenue statistics",
        "category": "Finance",
        "provider": "US Treasury",
        "authType": "none",
        "baseUrl": "https://api.fiscaldata.treasury.gov/services/api/fiscal_service",
        "cors": true,
        "endpoints": [
            {
                "name": "debtToday",
                "method": "GET",
                "path": "/v2/accounting/od/debt_to_penny",
                "params": [
                    {
                        "name": "sort",
                        "type": "string",
                        "required": false,
                        "desc": "-record_date"
                    }
                ]
            }
        ]
    },
    {
        "id": "pokeapi",
        "name": "PokéAPI",
        "description": "Pokémon data — species, abilities, types (great for demos/prototypes)",
        "category": "Development",
        "provider": "PokéAPI",
        "authType": "none",
        "baseUrl": "https://pokeapi.co/api/v2",
        "cors": true,
        "endpoints": [
            {
                "name": "getPokemon",
                "method": "GET",
                "path": "/pokemon/{name}",
                "params": [
                    {
                        "name": "name",
                        "type": "string",
                        "required": true,
                        "desc": "Pokémon name"
                    }
                ]
            }
        ]
    },
    {
        "id": "swapi",
        "name": "Star Wars API",
        "description": "Star Wars universe data (great for demos and testing)",
        "category": "Development",
        "provider": "SWAPI",
        "authType": "none",
        "baseUrl": "https://swapi.dev/api",
        "cors": true,
        "endpoints": [
            {
                "name": "getPeople",
                "method": "GET",
                "path": "/people",
                "params": []
            },
            {
                "name": "search",
                "method": "GET",
                "path": "/people",
                "params": [
                    {
                        "name": "search",
                        "type": "string",
                        "required": true,
                        "desc": "Name"
                    }
                ]
            }
        ]
    }
]